pykdeconnect/device_manager.py
pykdeconnect/exceptions.py
pykdeconnect/vol_extra.py
pykdeconnect/plugin_registry.py
pykdeconnect/helpers.py
pykdeconnect/devices.py
pykdeconnect/__init__.py
pykdeconnect/client.py
pykdeconnect/py.typed
pykdeconnect/__main__.py
pykdeconnect/const.py
pykdeconnect/protocols.py
pykdeconnect/payloads.py
pykdeconnect/storage.py
pykdeconnect/plugin.py
pykdeconnect/ssl_workaround.cpython-310-x86_64-linux-gnu.so
pykdeconnect/plugins/ping.py
pykdeconnect/plugins/__init__.py
pykdeconnect/plugins/battery.py
pykdeconnect-0.1.2a1.dist-info/WHEEL
pykdeconnect-0.1.2a1.dist-info/RECORD
pykdeconnect-0.1.2a1.dist-info/LICENSE.txt
pykdeconnect-0.1.2a1.dist-info/top_level.txt
pykdeconnect-0.1.2a1.dist-info/METADATA
pykdeconnect.libs/libcrypto-e3b25f79.so.1.1
pykdeconnect.libs/libssl-53b1ebe3.so.1.1
