Metadata-Version: 2.1
Name: pykdeconnect
Version: 0.1.2a1
Summary: A python implementation of the kdeconnect protocol
Home-page: https://github.com/freundTech/pykdeconnect
Author: Adrian Freund
Author-email: git@freundtech.com
License: MIT License
Keywords: kde,connect
Platform: UNKNOWN
Classifier: Development Status :: 3 - Alpha
Classifier: Intended Audience :: Developers
Classifier: Programming Language :: Python :: 3.9
Classifier: Programming Language :: Python :: 3.10
Classifier: Topic :: Utilities
Classifier: Typing :: Typed
Classifier: License :: OSI Approved :: MIT License
Requires-Python: >=3.9
License-File: LICENSE.txt
